stac_asset/__init__.py
stac_asset/_cli.py
stac_asset/_functions.py
stac_asset/blocking.py
stac_asset/client.py
stac_asset/config.py
stac_asset/earthdata_client.py
stac_asset/errors.py
stac_asset/filesystem_client.py
stac_asset/http_client.py
stac_asset/messages.py
stac_asset/planetary_computer_client.py
stac_asset/py.typed
stac_asset/s3_client.py
stac_asset/strategy.py
stac_asset/types.py
stac_asset/validate.py
stac_asset-0.4.7.dist-info/METADATA
stac_asset-0.4.7.dist-info/WHEEL
stac_asset-0.4.7.dist-info/entry_points.txt
stac_asset-0.4.7.dist-info/licenses/LICENSE
stac_asset-0.4.7.dist-info/licenses/NOTICE
stac_asset-0.4.7.dist-info/RECORD
