Metadata-Version: 2.4
Name: stac-asset
Version: 0.4.7
Summary: Read and download STAC assets across platforms and providers
Project-URL: Github, https://github.com/stac-utils/stac-asset
Project-URL: CHANGELOG, https://github.com/stac-utils/stac-asset/blob/main/CHANGELOG.md
Project-URL: Issues, https://github.com/stac-utils/stac-asset/issues
Author-email: Pete Gadomski <pete.gadomski@gmail.com>
License: Apache-2.0
License-File: LICENSE
License-File: NOTICE
Keywords: async,stac
Classifier: Development Status :: 4 - Beta
Classifier: License :: OSI Approved :: Apache Software License
Classifier: Programming Language :: Python :: 3
Classifier: Programming Language :: Python :: 3.10
Classifier: Programming Language :: Python :: 3.11
Classifier: Programming Language :: Python :: 3.12
Classifier: Programming Language :: Python :: 3.13
Requires-Python: >=3.10
Requires-Dist: aiobotocore>=2.5.0
Requires-Dist: aiofiles>=23.1.0
Requires-Dist: aiohttp-oauth2-client~=2.0
Requires-Dist: aiohttp-retry>=2.8.3
Requires-Dist: aiohttp~=3.12
Requires-Dist: pystac>=1.8.4
Requires-Dist: python-dateutil>=2.7.0
Requires-Dist: yarl>=1.9.2
Provides-Extra: cli
Requires-Dist: click-logging~=1.0.1; extra == 'cli'
Requires-Dist: click~=8.2.0; extra == 'cli'
Requires-Dist: tabulate~=0.9.0; extra == 'cli'
Requires-Dist: tqdm~=4.67.0; extra == 'cli'
